gitlab_search/__init__.py
gitlab_search/arguments.py
gitlab_search/config.py
gitlab_search/main.py
gitlab_search-0.1.0a4.dist-info/METADATA
gitlab_search-0.1.0a4.dist-info/WHEEL
gitlab_search-0.1.0a4.dist-info/entry_points.txt
gitlab_search-0.1.0a4.dist-info/licenses/LICENSE
gitlab_search-0.1.0a4.dist-info/RECORD
