Metadata-Version: 2.1
Name: gitlab-search
Version: 0.1.0a4
Summary: Command line tool for searching across GitLab projects
Project-URL: Homepage, https://gitlab.com/ErikKalkoken/gitlab-search
Project-URL: Bug Tracker, https://gitlab.com/ErikKalkoken/gitlab-search/issues
Author-email: Erik Kalkoken <kalkoken87@gmail.com>
License-File: LICENSE
Classifier: Environment :: Console
Classifier: Intended Audience :: Developers
Classifier: License :: OSI Approved :: MIT License
Classifier: Operating System :: OS Independent
Classifier: Programming Language :: Python :: 3
Classifier: Programming Language :: Python :: 3.10
Requires-Python: >=3.10
Requires-Dist: python-gitlab>=3.14
Requires-Dist: rich-argparse>=1.1.0
Requires-Dist: rich>=13.3.5
